.DS_Store
.gitignore
MANIFEST.in
README.rst
setup.py
docs/CHANGES.rst
docs/CONTRIBUTORS.rst
docs/LICENSE.GPL
docs/LICENSE.txt
src/lingua/__init__.py
src/lingua.autotranslate.egg-info/PKG-INFO
src/lingua.autotranslate.egg-info/SOURCES.txt
src/lingua.autotranslate.egg-info/dependency_links.txt
src/lingua.autotranslate.egg-info/entry_points.txt
src/lingua.autotranslate.egg-info/namespace_packages.txt
src/lingua.autotranslate.egg-info/not-zip-safe
src/lingua.autotranslate.egg-info/requires.txt
src/lingua.autotranslate.egg-info/top_level.txt
src/lingua/autotranslate/__init__.py
src/lingua/autotranslate/translator.py