Metadata-Version: 1.1
Name: lingua.autotranslate
Version: 0.2.1
Summary: An autotranslation toolkit for .po files using Google Translate API.
Home-page: https://github.com/saily/lingua.autotranslate
Author: Daniel Widerin
Author-email: daniel@widerin.net
License: GPL
Keywords: translation po gettext Babel lingua i18n
Platform: UNKNOWN
Classifier: Intended Audience :: Developers
Classifier: Operating System :: OS Independent
Classifier: Programming Language :: Python :: 2
Classifier: Programming Language :: Python :: 2.6
Classifier: Programming Language :: Python :: 2.7
Classifier: Topic :: Software Development :: Libraries :: Python Modules
